rohan/src/sram_32_512_scn4m_subm.v
// OpenRAM SRAM model
// Words: 512
// Word size: 32
// Write size: 1

`timescale 1ns/1ns

module sram_32_512_scn4m_subm(
// Port 0: RW
    clk0,csb0,web0,wmask0,addr0,din0,dout0
  );

  parameter NUM_WMASKS = 32 ;
  parameter DATA_WIDTH = 32 ;
  parameter ADDR_WIDTH = 9 ;
  parameter RAM_DEPTH = 1 << ADDR_WIDTH;
  // FIXME: This delay is arbitrary.
  parameter DELAY = 1 ;

  input  clk0; // clock
  input   csb0; // active low chip select
  input  web0; // active low write control
  input [NUM_WMASKS-1:0]   wmask0; // write mask
  input [ADDR_WIDTH-1:0]  addr0;
  input [DATA_WIDTH-1:0]  din0;
  output [DATA_WIDTH-1:0] dout0;

  reg  csb0_reg;
  reg  web0_reg;
  reg [NUM_WMASKS-1:0]   wmask0_reg;
  reg [ADDR_WIDTH-1:0]  addr0_reg;
  reg [DATA_WIDTH-1:0]  din0_reg;
  reg [DATA_WIDTH-1:0]  dout0;

  // All inputs are registers
  always @(posedge clk0)
  begin
    csb0_reg = csb0;
    web0_reg = web0;
    wmask0_reg = wmask0;
    addr0_reg = addr0;
    din0_reg = din0;
    dout0 = 32'bx;
    if ( !csb0_reg && web0_reg )
      $display($time," Reading %m addr0=%b dout0=%b",addr0_reg,mem[addr0_reg]);
    if ( !csb0_reg && !web0_reg )
      $display($time," Writing %m addr0=%b din0=%b wmask0=%b",addr0_reg,din0_reg,wmask0_reg);
  end

reg [DATA_WIDTH-1:0]    mem [0:RAM_DEPTH-1];

  // Memory Write Block Port 0
  // Write Operation : When web0 = 0, csb0 = 0
  always @ (negedge clk0)
  begin : MEM_WRITE0
    if ( !csb0_reg && !web0_reg ) begin
        if (wmask0_reg[0])
                mem[addr0_reg][0:0] = din0_reg[0:0];
        if (wmask0_reg[1])
                mem[addr0_reg][1:1] = din0_reg[1:1];
        if (wmask0_reg[2])
                mem[addr0_reg][2:2] = din0_reg[2:2];
        if (wmask0_reg[3])
                mem[addr0_reg][3:3] = din0_reg[3:3];
        if (wmask0_reg[4])
                mem[addr0_reg][4:4] = din0_reg[4:4];
        if (wmask0_reg[5])
                mem[addr0_reg][5:5] = din0_reg[5:5];
        if (wmask0_reg[6])
                mem[addr0_reg][6:6] = din0_reg[6:6];
        if (wmask0_reg[7])
                mem[addr0_reg][7:7] = din0_reg[7:7];
        if (wmask0_reg[8])
                mem[addr0_reg][8:8] = din0_reg[8:8];
        if (wmask0_reg[9])
                mem[addr0_reg][9:9] = din0_reg[9:9];
        if (wmask0_reg[10])
                mem[addr0_reg][10:10] = din0_reg[10:10];
        if (wmask0_reg[11])
                mem[addr0_reg][11:11] = din0_reg[11:11];
        if (wmask0_reg[12])
                mem[addr0_reg][12:12] = din0_reg[12:12];
        if (wmask0_reg[13])
                mem[addr0_reg][13:13] = din0_reg[13:13];
        if (wmask0_reg[14])
                mem[addr0_reg][14:14] = din0_reg[14:14];
        if (wmask0_reg[15])
                mem[addr0_reg][15:15] = din0_reg[15:15];
        if (wmask0_reg[16])
                mem[addr0_reg][16:16] = din0_reg[16:16];
        if (wmask0_reg[17])
                mem[addr0_reg][17:17] = din0_reg[17:17];
        if (wmask0_reg[18])
                mem[addr0_reg][18:18] = din0_reg[18:18];
        if (wmask0_reg[19])
                mem[addr0_reg][19:19] = din0_reg[19:19];
        if (wmask0_reg[20])
                mem[addr0_reg][20:20] = din0_reg[20:20];
        if (wmask0_reg[21])
                mem[addr0_reg][21:21] = din0_reg[21:21];
        if (wmask0_reg[22])
                mem[addr0_reg][22:22] = din0_reg[22:22];
        if (wmask0_reg[23])
                mem[addr0_reg][23:23] = din0_reg[23:23];
        if (wmask0_reg[24])
                mem[addr0_reg][24:24] = din0_reg[24:24];
        if (wmask0_reg[25])
                mem[addr0_reg][25:25] = din0_reg[25:25];
        if (wmask0_reg[26])
                mem[addr0_reg][26:26] = din0_reg[26:26];
        if (wmask0_reg[27])
                mem[addr0_reg][27:27] = din0_reg[27:27];
        if (wmask0_reg[28])
                mem[addr0_reg][28:28] = din0_reg[28:28];
        if (wmask0_reg[29])
                mem[addr0_reg][29:29] = din0_reg[29:29];
        if (wmask0_reg[30])
                mem[addr0_reg][30:30] = din0_reg[30:30];
        if (wmask0_reg[31])
                mem[addr0_reg][31:31] = din0_reg[31:31];
    end
  end

  // Memory Read Block Port 0
  // Read Operation : When web0 = 1, csb0 = 0
  always @ (negedge clk0)
  begin : MEM_READ0
    if (!csb0_reg && web0_reg)
       dout0 <= #(DELAY) mem[addr0_reg];
  end

endmodule

rohan/src/output_shifter.v
module output_shifter (
  // Based on conf and address, take appropriate bits of D and shift onto LSB's of d_out
  input wire [31:0] D,
  input wire [2:0] conf,
  input wire [4:0] addr,

  output reg [31:0] dout

  /***********
  conf map:
  000: 1k x 32
  001: 2k x 16
  010: 4k x 8
  011: 8k x 4
  100: 16k x 2
  101: 32k x 1
  *************/
  );

  // conf 000 is only conf where we care about top 16 bits of dout
  // top 16 bits of dout are always top 16 bits of D
  // assign dout[31:16] = D[31:16];

  // conf 000 and conf 001 is the only conf where we care about next 8 bits of dout
  // conf 000: dout[15:8] = D[15:8];
  // conf 001: dout[15:8] = addr[0] ? D[31:24] : D[15:8]; 
  // assign dout[15:8] = (conf == 3'b001 && addr[0]) ? D[31:24] : D[15:8];

  always @(*) begin
    dout[31:16] = D[31:16];
    if (conf == 3'b001 && addr[0]) dout[15:8] = D[31:24];
    else dout[15:8] = D[15:8];
    case(conf)
      3'b000: dout[7:0] = D[7:0];
      3'b001: begin
        if (!addr[0]) dout[7:0] = D[7:0];
        else if (addr[0]) dout[7:0] = D[23:16];
        else dout[7:0] = D[7:0];
      end
      3'b010: begin
        if (addr[1:0] == 2'b00) dout[7:0] = D[7:0];
        else if (addr[1:0] == 2'b01) dout[7:0] = D[15:8];
        else if (addr[1:0] == 2'b10) dout[7:0] = D[23:16];
        else if (addr[1:0] == 2'b11) dout[7:0] = D[31:24];
        else dout[7:0] = D[7:0];
      end
      3'b011: begin
        if (addr[2:0] == 3'b000) dout[7:0] = {2{D[3:0]}};
        else if (addr[2:0] == 3'b001) dout[7:0] = {2{D[7:4]}};
        else if (addr[2:0] == 3'b010) dout[7:0] = {2{D[11:7]}};
        else if (addr[2:0] == 3'b011) dout[7:0] = {2{D[15:12]}};
        else if (addr[2:0] == 3'b100) dout[7:0] = {2{D[19:16]}};
        else if (addr[2:0] == 3'b101) dout[7:0] = {2{D[23:20]}};
        else if (addr[2:0] == 3'b110) dout[7:0] = {2{D[27:24]}};
        else if (addr[2:0] == 3'b111) dout[7:0] = {2{D[31:28]}};
        else dout[7:0] = D[7:0];
      end
      3'b100: begin
        if (addr[3:0] == 4'b0000) dout[7:0] = {4{D[1:0]}};
        else if (addr[3:0] == 4'b0001) dout[7:0] = {4{D[3:2]}};
        else if (addr[3:0] == 4'b0010) dout[7:0] = {4{D[5:4]}};
        else if (addr[3:0] == 4'b0011) dout[7:0] = {4{D[7:6]}};
        else if (addr[3:0] == 4'b0100) dout[7:0] = {4{D[9:8]}};
        else if (addr[3:0] == 4'b0101) dout[7:0] = {4{D[11:10]}};
        else if (addr[3:0] == 4'b0110) dout[7:0] = {4{D[13:12]}};
        else if (addr[3:0] == 4'b0111) dout[7:0] = {4{D[15:14]}};
        else if (addr[3:0] == 4'b1000) dout[7:0] = {4{D[17:4]}};
        else if (addr[3:0] == 4'b1001) dout[7:0] = {4{D[19:18]}};
        else if (addr[3:0] == 4'b1010) dout[7:0] = {4{D[21:20]}};
        else if (addr[3:0] == 4'b1011) dout[7:0] = {4{D[23:22]}};
        else if (addr[3:0] == 4'b1100) dout[7:0] = {4{D[25:24]}};
        else if (addr[3:0] == 4'b1101) dout[7:0] = {4{D[27:26]}};
        else if (addr[3:0] == 4'b1110) dout[7:0] = {4{D[29:28]}};
        else if (addr[3:0] == 4'b1111) dout[7:0] = {4{D[31:30]}};
        else dout[7:0] = D[7:0];
      end
      3'b101: begin
        if (addr[4:0] == 5'b00000) dout[7:0] = {8{D[0]}};
        else if (addr[4:0] == 5'b00001) dout[7:0] = {8{D[1]}};
        else if (addr[4:0] == 5'b00010) dout[7:0] = {8{D[2]}};
        else if (addr[4:0] == 5'b00011) dout[7:0] = {8{D[3]}};
        else if (addr[4:0] == 5'b00100) dout[7:0] = {8{D[4]}};
        else if (addr[4:0] == 5'b00101) dout[7:0] = {8{D[5]}};
        else if (addr[4:0] == 5'b00110) dout[7:0] = {8{D[6]}};
        else if (addr[4:0] == 5'b00111) dout[7:0] = {8{D[7]}};
        else if (addr[4:0] == 5'b01000) dout[7:0] = {8{D[8]}};
        else if (addr[4:0] == 5'b01001) dout[7:0] = {8{D[9]}};
        else if (addr[4:0] == 5'b01010) dout[7:0] = {8{D[10]}};
        else if (addr[4:0] == 5'b01011) dout[7:0] = {8{D[11]}};
        else if (addr[4:0] == 5'b01100) dout[7:0] = {8{D[12]}};
        else if (addr[4:0] == 5'b01101) dout[7:0] = {8{D[13]}};
        else if (addr[4:0] == 5'b01110) dout[7:0] = {8{D[14]}};
        else if (addr[4:0] == 5'b01111) dout[7:0] = {8{D[15]}};
        else if (addr[4:0] == 5'b10000) dout[7:0] = {8{D[16]}};
        else if (addr[4:0] == 5'b10001) dout[7:0] = {8{D[17]}};
        else if (addr[4:0] == 5'b10010) dout[7:0] = {8{D[18]}};
        else if (addr[4:0] == 5'b10011) dout[7:0] = {8{D[19]}};
        else if (addr[4:0] == 5'b10100) dout[7:0] = {8{D[20]}};
        else if (addr[4:0] == 5'b10101) dout[7:0] = {8{D[21]}};
        else if (addr[4:0] == 5'b10110) dout[7:0] = {8{D[22]}};
        else if (addr[4:0] == 5'b10111) dout[7:0] = {8{D[23]}};
        else if (addr[4:0] == 5'b11000) dout[7:0] = {8{D[24]}};
        else if (addr[4:0] == 5'b11001) dout[7:0] = {8{D[25]}};
        else if (addr[4:0] == 5'b11010) dout[7:0] = {8{D[26]}};
        else if (addr[4:0] == 5'b11011) dout[7:0] = {8{D[27]}};
        else if (addr[4:0] == 5'b11100) dout[7:0] = {8{D[28]}};
        else if (addr[4:0] == 5'b11101) dout[7:0] = {8{D[29]}};
        else if (addr[4:0] == 5'b11110) dout[7:0] = {8{D[30]}};
        else if (addr[4:0] == 5'b11111) dout[7:0] = {8{D[31]}};
        else dout[7:0] = D[7:0];
      end
      default: dout[7:0] = D[7:0];
    endcase
  end

endmodule

src/unit_SRAM_dp/input_shifter.v
module input_shifter (
  // Based on config, repeat appropriate LSB's of D across 32 bits of d_in
  input wire [31:0] D,
  input wire [2:0] conf,

  output reg [31:0] din

  /***********
  Config map:
  000: 1k x 32 (c32)
  001: 2k x 16
  010: 4k x 8
  011: 8k x 4
  100: 16k x 2
  101: 32k x 1
  *************/
  );

  always @(*) begin
    case(conf)
      3'b000: din = D;
      3'b001: din = {2{D[15:0]}};
      3'b010: din = {4{D[7:0]}};
      3'b011: din = {8{D[3:0]}};
      3'b100: din = {16{D[1:0]}};
      3'b101: din = {32{D[0]}};
      default: din = {32{D[0]}};
    endcase
  end

endmodule

rohan/src/bl_mask.v
// Generate write mask
module bl_mask (
  input wire [4:0] addr,
  input wire [2:0] conf,

  output reg [31:0] mask

  /***********
  conf map:
  000: 1k x 32
  001: 2k x 16
  010: 4k x 8
  011: 8k x 4
  100: 16k x 2
  101: 32k x 1
  *************/
  );


  always @(*) begin
    case (conf[2:0])
      3'b000: mask = {32{1'b1}};
      3'b001: begin
        if (!addr[0]) mask = {{16{1'b0}}, {16{1'b1}}};
        else if (addr[0]) mask = {{16{1'b1}}, {16{1'b0}}};
      end
      3'b010: begin
        if (addr[1:0] == 2'b00) mask = {{24{1'b0}}, {8{1'b1}}};
        else if (addr[1:0] == 2'b01) mask = {{16{1'b0}}, {8{1'b1}}, {8{1'b0}}};
        else if (addr[1:0] == 2'b10) mask = {{8{1'b0}}, {8{1'b1}}, {16{1'b0}}};
        else if (addr[1:0] == 2'b11) mask = {{8{1'b1}}, {24{1'b0}}};
      end
      3'b011: begin
        if (addr[2:0] == 3'b000) mask = {{28{1'b0}}, {4{1'b1}}};
        else if (addr[2:0] == 3'b001) mask = {{24{1'b0}}, {4{1'b1}}, {4{1'b0}}};
        else if (addr[2:0] == 3'b010) mask = {{20{1'b0}}, {4{1'b1}}, {8{1'b0}}};
        else if (addr[2:0] == 3'b011) mask = {{16{1'b0}}, {4{1'b1}}, {12{1'b0}}};
        else if (addr[2:0] == 3'b100) mask = {{12{1'b0}}, {4{1'b1}}, {16{1'b0}}};
        else if (addr[2:0] == 3'b101) mask = {{8{1'b0}}, {4{1'b1}}, {20{1'b0}}};
        else if (addr[2:0] == 3'b110) mask = {{4{1'b0}}, {4{1'b1}}, {24{1'b0}}};
        else if (addr[2:0] == 3'b111) mask = {{4{1'b1}}, {28{1'b0}}};
      end
      3'b100: begin
        if (addr[3:0] == 4'b000) mask = {{30{1'b0}}, {2{1'b1}}};
        else if (addr[3:0] == 4'b0001) mask = {{28{1'b0}}, {2{1'b1}}, {2{1'b0}}};
        else if (addr[3:0] == 4'b0010) mask = {{26{1'b0}}, {2{1'b1}}, {4{1'b0}}};
        else if (addr[3:0] == 4'b0011) mask = {{24{1'b0}}, {2{1'b1}}, {6{1'b0}}};
        else if (addr[3:0] == 4'b0100) mask = {{22{1'b0}}, {2{1'b1}}, {8{1'b0}}};
        else if (addr[3:0] == 4'b0101) mask = {{20{1'b0}}, {2{1'b1}}, {10{1'b0}}};
        else if (addr[3:0] == 4'b0110) mask = {{18{1'b0}}, {2{1'b1}}, {12{1'b0}}};
        else if (addr[3:0] == 4'b0111) mask = {{16{1'b0}}, {2{1'b1}}, {14{1'b0}}};
        else if (addr[3:0] == 4'b1000) mask = {{14{1'b0}}, {2{1'b1}}, {16{1'b0}}};
        else if (addr[3:0] == 4'b1001) mask = {{12{1'b0}}, {2{1'b1}}, {18{1'b0}}};
        else if (addr[3:0] == 4'b1010) mask = {{10{1'b0}}, {2{1'b1}}, {20{1'b0}}};
        else if (addr[3:0] == 4'b1011) mask = {{8{1'b0}}, {2{1'b1}}, {22{1'b0}}};
        else if (addr[3:0] == 4'b1100) mask = {{6{1'b0}}, {2{1'b1}}, {24{1'b0}}};
        else if (addr[3:0] == 4'b1101) mask = {{4{1'b0}}, {2{1'b1}}, {26{1'b0}}};
        else if (addr[3:0] == 4'b1110) mask = {{2{1'b0}}, {2{1'b1}}, {28{1'b0}}};
        else if (addr[3:0] == 4'b1111) mask = {{2{1'b1}}, {30{1'b0}}};
      end
      3'b101: begin
        if (addr[4:0] == 5'b00000) mask = {{31{1'b0}}, {1{1'b1}}};
        else if (addr[4:0] == 5'b00001) mask = {{30{1'b0}}, {1{1'b1}}, {1{1'b0}}};
        else if (addr[4:0] == 5'b00010) mask = {{29{1'b0}}, {1{1'b1}}, {2{1'b0}}};
        else if (addr[4:0] == 5'b00011) mask = {{28{1'b0}}, {1{1'b1}}, {3{1'b0}}};
        else if (addr[4:0] == 5'b00100) mask = {{27{1'b0}}, {1{1'b1}}, {4{1'b0}}};
        else if (addr[4:0] == 5'b00101) mask = {{26{1'b0}}, {1{1'b1}}, {5{1'b0}}};
        else if (addr[4:0] == 5'b00110) mask = {{25{1'b0}}, {1{1'b1}}, {6{1'b0}}};
        else if (addr[4:0] == 5'b00111) mask = {{24{1'b0}}, {1{1'b1}}, {7{1'b0}}};
        else if (addr[4:0] == 5'b01000) mask = {{23{1'b0}}, {1{1'b1}}, {8{1'b0}}};
        else if (addr[4:0] == 5'b01001) mask = {{22{1'b0}}, {1{1'b1}}, {9{1'b0}}};
        else if (addr[4:0] == 5'b01010) mask = {{21{1'b0}}, {1{1'b1}}, {10{1'b0}}};
        else if (addr[4:0] == 5'b01011) mask = {{20{1'b0}}, {1{1'b1}}, {11{1'b0}}};
        else if (addr[4:0] == 5'b01100) mask = {{19{1'b0}}, {1{1'b1}}, {12{1'b0}}};
        else if (addr[4:0] == 5'b01101) mask = {{18{1'b0}}, {1{1'b1}}, {13{1'b0}}};
        else if (addr[4:0] == 5'b01110) mask = {{17{1'b0}}, {1{1'b1}}, {14{1'b0}}};
        else if (addr[4:0] == 5'b01111) mask = {{16{1'b0}}, {1{1'b1}}, {15{1'b0}}};
        else if (addr[4:0] == 5'b10000) mask = {{15{1'b0}}, {1{1'b1}}, {16{1'b0}}};
        else if (addr[4:0] == 5'b10001) mask = {{14{1'b0}}, {1{1'b1}}, {17{1'b0}}};
        else if (addr[4:0] == 5'b10010) mask = {{13{1'b0}}, {1{1'b1}}, {18{1'b0}}};
        else if (addr[4:0] == 5'b10011) mask = {{12{1'b0}}, {1{1'b1}}, {19{1'b0}}};
        else if (addr[4:0] == 5'b10100) mask = {{11{1'b0}}, {1{1'b1}}, {20{1'b0}}};
        else if (addr[4:0] == 5'b10101) mask = {{10{1'b0}}, {1{1'b1}}, {21{1'b0}}};
        else if (addr[4:0] == 5'b10110) mask = {{9{1'b0}}, {1{1'b1}}, {22{1'b0}}};
        else if (addr[4:0] == 5'b10111) mask = {{8{1'b0}}, {1{1'b1}}, {23{1'b0}}};
        else if (addr[4:0] == 5'b11000) mask = {{7{1'b0}}, {1{1'b1}}, {24{1'b0}}};
        else if (addr[4:0] == 5'b11001) mask = {{6{1'b0}}, {1{1'b1}}, {25{1'b0}}};
        else if (addr[4:0] == 5'b11010) mask = {{5{1'b0}}, {1{1'b1}}, {26{1'b0}}};
        else if (addr[4:0] == 5'b11011) mask = {{4{1'b0}}, {1{1'b1}}, {27{1'b0}}};
        else if (addr[4:0] == 5'b11100) mask = {{3{1'b0}}, {1{1'b1}}, {28{1'b0}}};
        else if (addr[4:0] == 5'b11101) mask = {{2{1'b0}}, {1{1'b1}}, {29{1'b0}}};
        else if (addr[4:0] == 5'b11110) mask = {{1{1'b0}}, {1{1'b1}}, {30{1'b0}}};
        else if (addr[4:0] == 5'b11111) mask = {{1{1'b1}}, {31{1'b0}}};
      end
      default: mask = {32{1'b1}};
    endcase
  end

endmodule

rohan/src/sram_ifc.v
`include "/home/rohan/sram_team/rohan/src/bl_mask.v"
`include "/home/rohan/sram_team/rohan/src/input_shifter.v"
`include "/home/rohan/sram_team/rohan/src/output_shifter.v"

module sram_ifc (
  // from fabric
  input clk,
	input [31:0] d_fabric_in,
	input csb,
	input web,
	input [13:0] addr,
	input [2:0] conf,
  input out_reg,

  // for SRAM write
	output [31:0] d_sram_in,
	output [31:0] w_mask,

  // for SRAM write
	input [31:0] d_sram_out,
	output [31:0] d_fabric_out,

  //pipeline csb, web to sram
  output reg csb_sync,
  output reg web_sync,
  // Does this really need to be pipelined since we're pipeline csb and web?
  output reg [8:0] baseaddr_sync



  /******* SRAM pins ***************
  input  clk0; // clock
  input   csb0; // active low chip select
  input  web0; // active low write control
  input [NUM_WMASKS-1:0]   wmask0; // write mask
  input [ADDR_WIDTH-1:0]  addr0;
  input [DATA_WIDTH-1:0]  din0;
  output [DATA_WIDTH-1:0] dout0;
  ***********************************/
);

  wire [8:0] baseaddr;
  assign baseaddr = addr[8:0];
  wire [4:0] subaddr;
  assign subaddr = addr[13:9];

  // sync capture - pipeline stage 1 ---------------
  reg [31:0] d_fabric_in_sync;
  reg [4:0] subaddr_sync;
  reg [2:0] conf_sync;
  always @(posedge clk) begin
    d_fabric_in_sync <= d_fabric_in;
    csb_sync <= csb;
    web_sync <= web;
    baseaddr_sync <= baseaddr;
    subaddr_sync <= subaddr;
    conf_sync <= conf;
  end
  //------------------------------------------------

  bl_mask bl_mask_1 (
    .addr(subaddr_sync),
    .conf(conf_sync),
    .mask(w_mask)
  );

  input_shifter input_shifter_1 (
    .D(d_fabric_in_sync),
    .conf(conf_sync),
    .din(d_sram_in)
  );

  wire [31:0] d_fabric_out_noreg;
  reg [31:0] d_fabric_out_reg;
  assign d_fabric_out = out_reg ? d_fabric_out_reg : d_fabric_out_noreg;

  reg [2:0] conf_reg;
  reg [4:0] subaddr_reg;
  // Pipeline conf, subaddr to match timing of latching of web, csb, addr, din bits in sram block
  always @(posedge clk) begin
    conf_reg <= conf_sync;
    subaddr_reg <= subaddr_sync;
  end 


  output_shifter output_shifter_1 (
    .D(d_sram_out),
    .conf(conf_reg),
    .addr(subaddr_reg),
    .dout(d_fabric_out_noreg)
  );

  always @(posedge clk) begin
    d_fabric_out_reg <= d_fabric_out_noreg;
  end

endmodule

rohan/src/z1top.v
`include "/home/rohan/sram_team/rohan/src/sram_ifc.v"
`include "/home/rohan/sram_team/rohan/src/sram_32_512_scn4m_subm.v"

module z1top (
  input clk,
  input [31:0] d_fabric_in,
  input csb,
  input web,
  input [13:0] addr,
  input [2:0] conf,
  input out_reg,
  output [31:0] d_fabric_out
);

  wire [31:0] d_sram_in;
  wire [31:0] w_mask;
  wire [31:0] d_sram_out;
  wire [8:0] baseaddr_sync;
  wire csb_sync;
  wire web_sync;

  sram_ifc smiley (
    .clk(clk),
    .d_fabric_in(d_fabric_in),
    .csb(csb),
    .web(web),
    .addr(addr),
    .conf(conf),
    .d_sram_in(d_sram_in),
    .w_mask(w_mask),
    .d_sram_out(d_sram_out),
    .out_reg(out_reg),
    .d_fabric_out(d_fabric_out),
    .csb_sync(csb_sync),
    .web_sync(web_sync),
    .baseaddr_sync(baseaddr_sync)
  );

  sram_32_512_scn4m_subm sram (
    .clk0(clk),
    .csb0(csb_sync),
    .web0(web_sync),
    .wmask0(w_mask),
    .addr0(baseaddr_sync),
    .din0(d_sram_in),
    .dout0(d_sram_out)
  );

endmodule

rohan/sim/z1top_tb.v
`include "/home/rohan/sram_team/rohan/src/z1top.v"

`timescale 1ns/1ns

`define SECOND 1000000000
`define MS 1000000

module z1top_tb();

	reg clk, csb, web, out_reg;
	reg [31:0] D_in;
	reg [13:0] addr;
	reg [2:0] conf;

	wire [31:0] D_out;

	initial clk = 0;
	always #(4) clk = ~clk;

  z1top unit_sram(
  .clk(clk),
  .d_fabric_in(D_in),
  .csb(csb),
  .web(web),
  .addr(addr),
  .conf(conf),
  .out_reg(out_reg),
  .d_fabric_out(D_out)
  );

  initial begin
		$dumpfile("z1top_tb.vcd");
		$dumpvars(0,z1top_tb);

		#(2);
    out_reg = 1'b0;
		conf = 3'b000;
		addr = 14'd0;
		D_in = 32'hAABBCCDD;
		csb = 1'b0;
		web = 1'b0;   // write

    #(8)
		web = 1'b1;   // read 32'hAABBCCDD

    #(8);
    D_in = 32'h0000FFAB;
    web = 1'b0;    // write

    #(8)
    web = 1'b1;    // read 32'h0000FFAB

    #(8)
    $display("change config to single bit write");
    conf = 3'b101;
    addr = 14'b11111000000000;
    D_in = 32'hFFFFFFFF;   // write 1 to last bit
    web = 1'b0;   // write

    #(8)
    web = 1'b1;   // read 32'hFFFFFFFF since output shifter takes appropriate bits and shifts onto LSB's

    #(8)
    conf = 3'b000;     // read 32'h8000FFAB


		#(24);
    $display("repeat with registered output");
    out_reg = 1'b1;
    conf = 3'b000;
    addr = 14'd0;
    D_in = 32'hAABBCCDD;
    csb = 1'b0;
    web = 1'b0;   // write

    #(8)
    web = 1'b1;   // read

    #(8);
    D_in = 32'h0000FFAB;
    web = 1'b0;    // write

    #(8)
    web = 1'b1;    // read

    #(8)
    $display("change config to single bit write");
    conf = 3'b101;
    addr = 14'b11111000000000;
    D_in = 32'hFFFFFFFF;   // write 1 to last bit
    web = 1'b0;   // write

    #(8)
    web = 1'b1;   // read

    #(8)
    conf = 3'b000;
    

    #(24)
		$finish();
	end

endmodule

rohan/sim/z1top_tb.vcd
$date
	Tue Nov 24 17:37:42 2020
$end
$version
	Icarus Verilog
$end
$timescale
	1ns
$end
$scope module z1top_tb $end
$var wire 32 ! D_out [31:0] $end
$var reg 32 " D_in [31:0] $end
$var reg 14 # addr [13:0] $end
$var reg 1 $ clk $end
$var reg 3 % conf [2:0] $end
$var reg 1 & csb $end
$var reg 1 ' out_reg $end
$var reg 1 ( web $end
$scope module unit_sram $end
$var wire 14 ) addr [13:0] $end
$var wire 1 $ clk $end
$var wire 3 * conf [2:0] $end
$var wire 1 & csb $end
$var wire 32 + d_fabric_in [31:0] $end
$var wire 1 ' out_reg $end
$var wire 1 ( web $end
$var wire 1 , web_sync $end
$var wire 32 - w_mask [31:0] $end
$var wire 32 . d_sram_out [31:0] $end
$var wire 32 / d_sram_in [31:0] $end
$var wire 32 0 d_fabric_out [31:0] $end
$var wire 1 1 csb_sync $end
$var wire 9 2 baseaddr_sync [8:0] $end
$scope module smiley $end
$var wire 14 3 addr [13:0] $end
$var wire 1 $ clk $end
$var wire 3 4 conf [2:0] $end
$var wire 1 & csb $end
$var wire 32 5 d_fabric_in [31:0] $end
$var wire 1 ' out_reg $end
$var wire 1 ( web $end
$var wire 32 6 w_mask [31:0] $end
$var wire 5 7 subaddr [4:0] $end
$var wire 32 8 d_sram_out [31:0] $end
$var wire 32 9 d_sram_in [31:0] $end
$var wire 32 : d_fabric_out_noreg [31:0] $end
$var wire 32 ; d_fabric_out [31:0] $end
$var wire 9 < baseaddr [8:0] $end
$var reg 9 = baseaddr_sync [8:0] $end
$var reg 3 > conf_reg [2:0] $end
$var reg 3 ? conf_sync [2:0] $end
$var reg 1 1 csb_sync $end
$var reg 32 @ d_fabric_in_sync [31:0] $end
$var reg 32 A d_fabric_out_reg [31:0] $end
$var reg 5 B subaddr_reg [4:0] $end
$var reg 5 C subaddr_sync [4:0] $end
$var reg 1 , web_sync $end
$scope module bl_mask_1 $end
$var wire 5 D addr [4:0] $end
$var wire 3 E conf [2:0] $end
$var reg 32 F mask [31:0] $end
$upscope $end
$scope module input_shifter_1 $end
$var wire 32 G D [31:0] $end
$var wire 3 H conf [2:0] $end
$var reg 32 I din [31:0] $end
$upscope $end
$scope module output_shifter_1 $end
$var wire 5 J addr [4:0] $end
$var wire 3 K conf [2:0] $end
$var wire 32 L D [31:0] $end
$var reg 32 M dout [31:0] $end
$upscope $end
$upscope $end
$scope module sram $end
$var wire 9 N addr0 [8:0] $end
$var wire 1 $ clk0 $end
$var wire 1 1 csb0 $end
$var wire 32 O din0 [31:0] $end
$var wire 1 , web0 $end
$var wire 32 P wmask0 [31:0] $end
$var reg 9 Q addr0_reg [8:0] $end
$var reg 1 R csb0_reg $end
$var reg 32 S din0_reg [31:0] $end
$var reg 32 T dout0 [31:0] $end
$var reg 1 U web0_reg $end
$var reg 32 V wmask0_reg [31:0] $end
$scope begin MEM_READ0 $end
$upscope $end
$scope begin MEM_WRITE0 $end
$upscope $end
$upscope $end
$upscope $end
$upscope $end
$enddefinitions $end
#0
$dumpvars
bx V
xU
bx T
bx S
xR
bx Q
bx P
bx O
bx N
bx M
bx L
bx K
bx J
bx I
bx H
bx G
bx F
bx E
bx D
bx C
bx B
bx A
bx @
bx ?
bx >
bx =
bx <
bx ;
bx :
bx 9
bx 8
bx 7
bx 6
bx 5
bx 4
bx 3
bx 2
x1
bx 0
bx /
bx .
bx -
x,
bx +
bx *
bx )
x(
x'
x&
bx %
0$
bx #
bx "
bx !
$end
#2
b0 <
b0 7
0(
0&
b10101010101110111100110011011101 "
b10101010101110111100110011011101 +
b10101010101110111100110011011101 5
b0 #
b0 )
b0 3
b0 %
b0 *
b0 4
0'
#4
b11111111111111111111111111111111 -
b11111111111111111111111111111111 6
b11111111111111111111111111111111 F
b11111111111111111111111111111111 P
b10101010101110111100110011011101 /
b10101010101110111100110011011101 9
b10101010101110111100110011011101 I
b10101010101110111100110011011101 O
b0 ?
b0 E
b0 H
b0 C
b0 D
b0 2
b0 =
b0 N
0,
01
b10101010101110111100110011011101 @
b10101010101110111100110011011101 G
1$
#8
0$
#10
1(
#12
b0 B
b0 J
b0 >
b0 K
1,
b10101010101110111100110011011101 S
b0 Q
b11111111111111111111111111111111 V
0U
0R
1$
#16
0$
#18
0(
b1111111110101011 "
b1111111110101011 +
b1111111110101011 5
#20
b1111111110101011 /
b1111111110101011 9
b1111111110101011 I
b1111111110101011 O
0,
b1111111110101011 @
b1111111110101011 G
1U
1$
#24
0$
#25
b10101010101110111100110011011101 !
b10101010101110111100110011011101 0
b10101010101110111100110011011101 ;
b10101010101110111100110011011101 :
b10101010101110111100110011011101 M
b10101010101110111100110011011101 .
b10101010101110111100110011011101 8
b10101010101110111100110011011101 L
b10101010101110111100110011011101 T
#26
1(
#28
b10101010101110111100110011011101 A
1,
bx !
bx 0
bx ;
bx :
bx M
bx .
bx 8
bx L
bx T
b1111111110101011 S
0U
1$
#32
0$
#34
b11111 7
0(
b11111111111111111111111111111111 "
b11111111111111111111111111111111 +
b11111111111111111111111111111111 5
b11111000000000 #
b11111000000000 )
b11111000000000 3
b101 %
b101 *
b101 4
#36
b10000000000000000000000000000000 -
b10000000000000000000000000000000 6
b10000000000000000000000000000000 F
b10000000000000000000000000000000 P
b11111111111111111111111111111111 /
b11111111111111111111111111111111 9
b11111111111111111111111111111111 I
b11111111111111111111111111111111 O
b101 ?
b101 E
b101 H
b11111 C
b11111 D
0,
b11111111111111111111111111111111 @
b11111111111111111111111111111111 G
bx A
1U
1$
#40
0$
#41
b1111111110101011 !
b1111111110101011 0
b1111111110101011 ;
b1111111110101011 :
b1111111110101011 M
b1111111110101011 .
b1111111110101011 8
b1111111110101011 L
b1111111110101011 T
#42
1(
#44
b1111111110101011 A
b11111 B
b11111 J
b101 >
b101 K
1,
bx !
bx 0
bx ;
bx :
bx M
bx .
bx 8
bx L
bx T
b11111111111111111111111111111111 S
b10000000000000000000000000000000 V
0U
1$
#48
0$
#50
b0 %
b0 *
b0 4
#52
b11111111111111111111111111111111 -
b11111111111111111111111111111111 6
b11111111111111111111111111111111 F
b11111111111111111111111111111111 P
b0 ?
b0 E
b0 H
bx A
1U
1$
#56
0$
